vhelpers/__init__.py
vhelpers/py.typed
vhelpers/types_.py
vhelpers/vdate.py
vhelpers/vdict.py
vhelpers/vint.py
vhelpers/vip.py
vhelpers/vlist.py
vhelpers/vparam.py
vhelpers/vpath.py
vhelpers/vre.py
vhelpers/vstr.py
vhelpers/vyml.py
vhelpers-0.3.0.dist-info/METADATA
vhelpers-0.3.0.dist-info/WHEEL
vhelpers-0.3.0.dist-info/RECORD
