Metadata-Version: 2.1
Name: vhelpers
Version: 0.3.0
Summary: Often used functions in vladimirs-git projects
Home-page: https://github.com/vladimirs-git/vhelpers
License: MIT
Author: Vladimir Prusakov
Author-email: vladimir.prusakovs@gmail.com
Requires-Python: >=3.8,<4.0
Classifier: Development Status :: 5 - Production/Stable
Classifier: Intended Audience :: Developers
Classifier: License :: OSI Approved :: MIT License
Classifier: Natural Language :: English
Classifier: Programming Language :: Python :: 3
Classifier: Programming Language :: Python :: 3.8
Classifier: Programming Language :: Python :: 3.9
Classifier: Programming Language :: Python :: 3.10
Classifier: Programming Language :: Python :: 3.11
Classifier: Programming Language :: Python :: 3.12
Provides-Extra: test
Requires-Dist: tomli (>=2.0.1,<3.0.0)
Project-URL: Bug Tracker, https://github.com/vladimirs-git/vhelpers/issues
Project-URL: Download URL, https://github.com/vladimirs-git/vhelpers/archive/refs/tags/0.3.0.tar.gz
Project-URL: Repository, https://github.com/vladimirs-git/vhelpers
